[{"node":{"avatar_large":"https://cdn.v2ex.com/navatar/94f6/d7e0/300_large.png?m=1614829460","name":"programmer","avatar_normal":"https://cdn.v2ex.com/navatar/94f6/d7e0/300_normal.png?m=1614829460","title":"程序员","url":"https://www.v2ex.com/go/programmer","topics":43807,"footer":"","header":"While code monkeys are not eating bananas, they're coding.","title_alternative":"Programmer","avatar_mini":"https://cdn.v2ex.com/navatar/94f6/d7e0/300_mini.png?m=1614829460","stars":7296,"aliases":[],"root":false,"id":300,"parent_node_name":"computer"},"member":{"username":"LeroyMooney","website":"","github":"","psn":"","avatar_normal":"https://cdn.v2ex.com/avatar/7451/6b67/422937_mini.png?m=1594457333","bio":"","url":"https://www.v2ex.com/u/LeroyMooney","tagline":"","twitter":"","created":1560907972,"avatar_large":"https://cdn.v2ex.com/avatar/7451/6b67/422937_mini.png?m=1594457333","avatar_mini":"https://cdn.v2ex.com/avatar/7451/6b67/422937_mini.png?m=1594457333","location":"","btc":"","id":422937},"last_reply_by":"xuanbg","last_touched":1616119285,"title":"新来的外包同事，这代码，我？？?","url":"https://www.v2ex.com/t/763063","created":1616117112,"content":"```\r\npublic List<IssueStatistics> getIssueStatistics() {\r\n    return issueStatistics == null ? null : issueStatistics;\r\n}\r\n```","content_rendered":"<pre><code>public List&lt;IssueStatistics&gt; getIssueStatistics() {\n    return issueStatistics == null ? null : issueStatistics;\n}\n</code></pre>\n","last_modified":1616117135,"replies":51,"id":763063},{"node":{"avatar_large":"https://cdn.v2ex.com/navatar/94f6/d7e0/300_large.png?m=1614829460","name":"programmer","avatar_normal":"https://cdn.v2ex.com/navatar/94f6/d7e0/300_normal.png?m=1614829460","title":"程序员","url":"https://www.v2ex.com/go/programmer","topics":43806,"footer":"","header":"While code monkeys are not eating bananas, they're coding.","title_alternative":"Programmer","avatar_mini":"https://cdn.v2ex.com/navatar/94f6/d7e0/300_mini.png?m=1614829460","stars":7296,"aliases":[],"root":false,"id":300,"parent_node_name":"computer"},"member":{"username":"Ivone29","website":"https://ivone.me/","github":"","psn":"","avatar_normal":"https://cdn.v2ex.com/avatar/0e4a/e2a6/409411_mini.png?m=1559713272","bio":"","url":"https://www.v2ex.com/u/Ivone29","tagline":"","twitter":"","created":1557130155,"avatar_large":"https://cdn.v2ex.com/avatar/0e4a/e2a6/409411_mini.png?m=1559713272","avatar_mini":"https://cdn.v2ex.com/avatar/0e4a/e2a6/409411_mini.png?m=1559713272","location":"","btc":"","id":409411},"last_reply_by":"Biwood","last_touched":1616119202,"title":"大家会用工作和生活两个微信号吗？","url":"https://www.v2ex.com/t/763052","created":1616115999,"content":"","content_rendered":"","last_modified":1616115999,"replies":30,"id":763052},{"node":{"avatar_large":"https://cdn.v2ex.com/navatar/d3d9/4468/10_large.png?m=1615111860","name":"mbp","avatar_normal":"https://cdn.v2ex.com/navatar/d3d9/4468/10_normal.png?m=1615111860","title":"MacBook Pro","url":"https://www.v2ex.com/go/mbp","topics":6869,"footer":"","header":"State-of-the-art processors. All-new graphics. Breakthrough high-speed I/O. Three very big leaps forward.","title_alternative":"MacBook Pro","avatar_mini":"https://cdn.v2ex.com/navatar/d3d9/4468/10_mini.png?m=1615111860","stars":2853,"aliases":[],"root":false,"id":10,"parent_node_name":"apple"},"member":{"username":"Pogbag","website":null,"github":"","psn":"","avatar_normal":"https://cdn.v2ex.com/avatar/a49b/0fdd/300244_mini.png?m=1609399441","bio":null,"url":"https://www.v2ex.com/u/Pogbag","tagline":null,"twitter":"","created":1521078466,"avatar_large":"https://cdn.v2ex.com/avatar/a49b/0fdd/300244_mini.png?m=1609399441","avatar_mini":"https://cdn.v2ex.com/avatar/a49b/0fdd/300244_mini.png?m=1609399441","location":null,"btc":"","id":300244},"last_reply_by":"paopaosa","last_touched":1616118273,"title":"老款 MacBook Pro 如何发挥余热","url":"https://www.v2ex.com/t/763053","created":1616116060,"content":"目前有一台 2013later 的 MacBook Pro ME865 2014 年刚工作时候买的 买的时候 8000 多 当时咬牙入手的 从没买过这么贵的电子产品 这么多年 一直运行流畅 最近升级到了 big sur 开始力不从心了 明显卡顿 出二手还有点舍不得 有升级方案吗 目前配置是 i5 4285U+8G+256G，不升级的话有其他发挥余热的方案吗？","content_rendered":"<p>目前有一台 2013later 的 MacBook Pro ME865 2014 年刚工作时候买的 买的时候 8000 多 当时咬牙入手的 从没买过这么贵的电子产品 这么多年 一直运行流畅 最近升级到了 big sur 开始力不从心了 明显卡顿 出二手还有点舍不得 有升级方案吗 目前配置是 i5 4285U+8G+256G，不升级的话有其他发挥余热的方案吗？</p>\n","last_modified":1616116109,"replies":21,"id":763053},{"node":{"avatar_large":"https://cdn.v2ex.com/navatar/093f/65e0/59_large.png?m=1615956453","name":"random","avatar_normal":"https://cdn.v2ex.com/navatar/093f/65e0/59_normal.png?m=1615956453","title":"随想","url":"https://www.v2ex.com/go/random","topics":2863,"footer":"","header":"有的时候，可以停下来找找灵感，然后再继续。","title_alternative":"Random","avatar_mini":"https://cdn.v2ex.com/navatar/093f/65e0/59_mini.png?m=1615956453","stars":901,"aliases":[],"root":false,"id":59,"parent_node_name":"v2ex"},"member":{"username":"vitovan","website":"VitoVan.com","github":"VitoVan","psn":"","avatar_normal":"https://cdn.v2ex.com/avatar/9366/088b/28986_mini.png?m=1613954226","bio":"豆瓣：猫猫驴\r\nhttps://www.douban.com/people/maomaolvloveyou/\r\n\r\n王伟宇宙：\r\nhttps://www.v2ex.com/p/3SS1131M\r\n\r\n年少无知时曾经口出轻狂，\r\n为免尴尬特意将列表隐藏，\r\n胡言乱语如果能博您一笑，\r\n上面的链接就是所有文章。","url":"https://www.v2ex.com/u/vitovan","tagline":"猫猫驴 - 沃贡诗人","twitter":"","created":1351401337,"avatar_large":"https://cdn.v2ex.com/avatar/9366/088b/28986_mini.png?m=1613954226","avatar_mini":"https://cdn.v2ex.com/avatar/9366/088b/28986_mini.png?m=1613954226","location":"银河系西旋臂末端","btc":"","id":28986},"last_reply_by":"idealhs","last_touched":1616118965,"title":"你是谁？我是▇▇","url":"https://www.v2ex.com/t/763034","created":1616112010,"content":"是谁，敲碎▇▇的▇▇，\r\n是谁，抚平▇▇的▇▇，\r\n\r\n是谁，拿走▇▇的▇▇，\r\n又是谁，把▇▇，轻轻送回。\r\n\r\n这是没有▇▇的▇▇▇句，\r\n这是没有▇▇的▇▇▇诗。\r\n\r\n我在▇▇的▇▇上灰飞烟灭，\r\n你在▇▇的▇▇里支离破碎。\r\n\r\n我看见▇▇，你看见▇▇。\r\n\r\n是▇，送来▇▇的▇▇，\r\n是▇，带走▇▇的▇▇。\r\n\r\n▇，不是▇▇▇▇的▇▇，\r\n▇，不是▇▇▇▇的▇▇。\r\n\r\n你是谁？\r\n我是▇▇。","content_rendered":"是谁，敲碎▇▇的▇▇，<br />是谁，抚平▇▇的▇▇，<br /><br />是谁，拿走▇▇的▇▇，<br />又是谁，把▇▇，轻轻送回。<br /><br />这是没有▇▇的▇▇▇句，<br />这是没有▇▇的▇▇▇诗。<br /><br />我在▇▇的▇▇上灰飞烟灭，<br />你在▇▇的▇▇里支离破碎。<br /><br />我看见▇▇，你看见▇▇。<br /><br />是▇，送来▇▇的▇▇，<br />是▇，带走▇▇的▇▇。<br /><br />▇，不是▇▇▇▇的▇▇，<br />▇，不是▇▇▇▇的▇▇。<br /><br />你是谁？<br />我是▇▇。","last_modified":1616112115,"replies":20,"id":763034},{"node":{"avatar_large":"https://cdn.v2ex.com/navatar/94f6/d7e0/300_large.png?m=1614829460","name":"programmer","avatar_normal":"https://cdn.v2ex.com/navatar/94f6/d7e0/300_normal.png?m=1614829460","title":"程序员","url":"https://www.v2ex.com/go/programmer","topics":43806,"footer":"","header":"While code monkeys are not eating bananas, they're coding.","title_alternative":"Programmer","avatar_mini":"https://cdn.v2ex.com/navatar/94f6/d7e0/300_mini.png?m=1614829460","stars":7296,"aliases":[],"root":false,"id":300,"parent_node_name":"computer"},"member":{"username":"boyuanhao","website":null,"github":null,"psn":null,"avatar_normal":"https://cdn.v2ex.com/avatar/cab9/a6f7/363093_mini.png?m=1542353217","bio":null,"url":"https://www.v2ex.com/u/boyuanhao","tagline":null,"twitter":null,"created":1542178469,"avatar_large":"https://cdn.v2ex.com/avatar/cab9/a6f7/363093_mini.png?m=1542353217","avatar_mini":"https://cdn.v2ex.com/avatar/cab9/a6f7/363093_mini.png?m=1542353217","location":null,"btc":null,"id":363093},"last_reply_by":"jntitor","last_touched":1616076080,"title":"我中奖了？！","url":"https://www.v2ex.com/t/763057","created":1616116327,"content":"早上用花小猪打车后跳出抽奖界面，习惯性点了一下，发现中了下面这个扫地机器人，屌丝心理作祟，该不会真的中奖了吧？ 还是花小猪的套路？\r\n\r\nhttps://imgtu.com/i/6RfNKx","content_rendered":"早上用花小猪打车后跳出抽奖界面，习惯性点了一下，发现中了下面这个扫地机器人，屌丝心理作祟，该不会真的中奖了吧？ 还是花小猪的套路？<br /><br /><a target=\"_blank\" href=\"https://imgtu.com/i/6RfNKx\" rel=\"nofollow noopener\">https://imgtu.com/i/6RfNKx</a>","last_modified":1616116327,"replies":12,"id":763057},{"node":{"avatar_large":"https://cdn.v2ex.com/navatar/c9f0/f895/8_large.png?m=1615111905","name":"iphone","avatar_normal":"https://cdn.v2ex.com/navatar/c9f0/f895/8_normal.png?m=1615111905","title":"iPhone","url":"https://www.v2ex.com/go/iphone","topics":8396,"footer":"这里绝不讨论如何获得 iPhone 盗版软件、iTunes 黑卡之类。","header":"Say hello to the future.","title_alternative":"iPhone","avatar_mini":"https://cdn.v2ex.com/navatar/c9f0/f895/8_mini.png?m=1615111905","stars":2620,"aliases":[],"root":false,"id":8,"parent_node_name":"apple"},"member":{"username":"Apple2023","website":"","github":null,"psn":null,"avatar_normal":"https://cdn.v2ex.com/avatar/54c4/8265/495791_mini.png?m=1612710190","bio":"","url":"https://www.v2ex.com/u/Apple2023","tagline":"","twitter":null,"created":1592789519,"avatar_large":"https://cdn.v2ex.com/avatar/54c4/8265/495791_mini.png?m=1612710190","avatar_mini":"https://cdn.v2ex.com/avatar/54c4/8265/495791_mini.png?m=1612710190","location":"","btc":null,"id":495791},"last_reply_by":"doveyoung","last_touched":1616059135,"title":"选择 Firefox 还是 Chrome？","url":"https://www.v2ex.com/t/763037","created":1616113197,"content":"使用 Chrome 好多年了，最近想试试 Firefox 。有没有人介绍下 firefox","content_rendered":"使用 Chrome 好多年了，最近想试试 Firefox 。有没有人介绍下 firefox","last_modified":1616113197,"replies":10,"id":763037},{"node":{"avatar_large":"https://cdn.v2ex.com/navatar/d3d9/4468/10_large.png?m=1615111860","name":"mbp","avatar_normal":"https://cdn.v2ex.com/navatar/d3d9/4468/10_normal.png?m=1615111860","title":"MacBook Pro","url":"https://www.v2ex.com/go/mbp","topics":6869,"footer":"","header":"State-of-the-art processors. All-new graphics. Breakthrough high-speed I/O. Three very big leaps forward.","title_alternative":"MacBook Pro","avatar_mini":"https://cdn.v2ex.com/navatar/d3d9/4468/10_mini.png?m=1615111860","stars":2853,"aliases":[],"root":false,"id":10,"parent_node_name":"apple"},"member":{"username":"FKTHECCP","website":null,"github":null,"psn":null,"avatar_normal":"https://cdn.v2ex.com/avatar/499f/37d9/522336_mini.png?m=1614929648","bio":null,"url":"https://www.v2ex.com/u/FKTHECCP","tagline":null,"twitter":null,"created":1607083321,"avatar_large":"https://cdn.v2ex.com/avatar/499f/37d9/522336_mini.png?m=1614929648","avatar_mini":"https://cdn.v2ex.com/avatar/499f/37d9/522336_mini.png?m=1614929648","location":null,"btc":null,"id":522336},"last_reply_by":"sayid233","last_touched":1616118055,"title":"M1 MacBook 玩 steam 上的游戏体验如何？","url":"https://www.v2ex.com/t/763035","created":1616112251,"content":"15 年的 Pro，随便开个什么游戏都是风扇狂转，噪音无法忍受，已经很久没开过游戏了。\r\n好奇 M1 的类似表现如何呢。","content_rendered":"15 年的 Pro，随便开个什么游戏都是风扇狂转，噪音无法忍受，已经很久没开过游戏了。<br />好奇 M1 的类似表现如何呢。","last_modified":1616112251,"replies":10,"id":763035},{"node":{"avatar_large":"https://cdn.v2ex.com/navatar/c20a/d4d7/12_large.png?m=1615112532","name":"qna","avatar_normal":"https://cdn.v2ex.com/navatar/c20a/d4d7/12_normal.png?m=1615112532","title":"问与答","url":"https://www.v2ex.com/go/qna","topics":170337,"footer":"","header":"一个更好的世界需要你持续地提出好问题。","title_alternative":"Questions and Answers","avatar_mini":"https://cdn.v2ex.com/navatar/c20a/d4d7/12_mini.png?m=1615112532","stars":3188,"aliases":[],"root":false,"id":12,"parent_node_name":"v2ex"},"member":{"username":"yangwii","website":null,"github":null,"psn":null,"avatar_normal":"https://cdn.v2ex.com/gravatar/65d5334a387c24d86a6c6068f01f903d?s=24&d=retro","bio":null,"url":"https://www.v2ex.com/u/yangwii","tagline":null,"twitter":null,"created":1521029380,"avatar_large":"https://cdn.v2ex.com/gravatar/65d5334a387c24d86a6c6068f01f903d?s=24&d=retro","avatar_mini":"https://cdn.v2ex.com/gravatar/65d5334a387c24d86a6c6068f01f903d?s=24&d=retro","location":null,"btc":null,"id":300115},"last_reply_by":"redtea","last_touched":1616118983,"title":"如何将 Binance 上的数字币提现？","url":"https://www.v2ex.com/t/763058","created":1616116475,"content":"多年前在某平台图好玩买了一些数字币，不多 2000 块钱，后期因为担心平台跑路，就把货币都转到 Binance 上去了，\r\n最近看了看，随着 BTC 的春风翻倍了，想着把钱取出来清明节出去转一转，自己弄了半天不知道咋弄？\r\n有高人给支个招吗？","content_rendered":"<p>多年前在某平台图好玩买了一些数字币，不多 2000 块钱，后期因为担心平台跑路，就把货币都转到 Binance 上去了，\n最近看了看，随着 BTC 的春风翻倍了，想着把钱取出来清明节出去转一转，自己弄了半天不知道咋弄？\n有高人给支个招吗？</p>\n","last_modified":1616116475,"replies":9,"id":763058},{"node":{"avatar_large":"https://cdn.v2ex.com/navatar/27ed/0fb9/1039_large.png?m=1601353687","name":"k8s","avatar_normal":"https://cdn.v2ex.com/navatar/27ed/0fb9/1039_normal.png?m=1601353687","title":"Kubernetes","url":"https://www.v2ex.com/go/k8s","topics":184,"footer":"","header":"适用于大规模生产环境的容器编排管理平台。","title_alternative":"Kubernetes","avatar_mini":"https://cdn.v2ex.com/navatar/27ed/0fb9/1039_mini.png?m=1601353687","stars":294,"aliases":[],"root":false,"id":1039,"parent_node_name":"cloud"},"member":{"username":"zhoudaiyu","website":"","github":"","psn":"","avatar_normal":"https://cdn.v2ex.com/avatar/b75f/9ee0/163414_mini.png?m=1574570790","bio":"","url":"https://www.v2ex.com/u/zhoudaiyu","tagline":"","twitter":"","created":1458024699,"avatar_large":"https://cdn.v2ex.com/avatar/b75f/9ee0/163414_mini.png?m=1574570790","avatar_mini":"https://cdn.v2ex.com/avatar/b75f/9ee0/163414_mini.png?m=1574570790","location":"","btc":"","id":163414},"last_reply_by":"UN2758","last_touched":1616118164,"title":"为什么 K8S 要求 Pod 中的 Container 启动时至少有一个进程是前台运行的？","url":"https://www.v2ex.com/t/763043","created":1616114588,"content":"不是很明白为什么必须前台，如果有的进程就是只能后台启动的，那怎么办呢？","content_rendered":"<p>不是很明白为什么必须前台，如果有的进程就是只能后台启动的，那怎么办呢？</p>\n","last_modified":1616114588,"replies":9,"id":763043},{"node":{"avatar_large":"https://cdn.v2ex.com/navatar/94f6/d7e0/300_large.png?m=1614829460","name":"programmer","avatar_normal":"https://cdn.v2ex.com/navatar/94f6/d7e0/300_normal.png?m=1614829460","title":"程序员","url":"https://www.v2ex.com/go/programmer","topics":43806,"footer":"","header":"While code monkeys are not eating bananas, they're coding.","title_alternative":"Programmer","avatar_mini":"https://cdn.v2ex.com/navatar/94f6/d7e0/300_mini.png?m=1614829460","stars":7296,"aliases":[],"root":false,"id":300,"parent_node_name":"computer"},"member":{"username":"llyichT","website":"","github":null,"psn":null,"avatar_normal":"https://cdn.v2ex.com/avatar/7c3a/f7f8/532575_mini.png?m=1616111629","bio":"Hello, World!\r\nwww.v2ex.com","url":"https://www.v2ex.com/u/llyichT","tagline":"","twitter":null,"created":1612745890,"avatar_large":"https://cdn.v2ex.com/avatar/7c3a/f7f8/532575_mini.png?m=1616111629","avatar_mini":"https://cdn.v2ex.com/avatar/7c3a/f7f8/532575_mini.png?m=1616111629","location":"","btc":null,"id":532575},"last_reply_by":"llyichT","last_touched":1616118590,"title":"迫于没有备案，用 Vercel 给国内云服务器当前端，速度不错","url":"https://www.v2ex.com/t/763047","created":1616114988,"content":"如题。\r\n\r\n想搭些网站，买海外服务器太贵，买国内服务器又需要备案，研究了一下，最终决定买国内活动服务器，用 Vercel 作前端。\r\n\r\nVercel 类似 Cloudflare Workers，支持 serverless code 和边缘缓存，相当于在上面跑了个反代，同时开启了缓存。\r\n\r\n```\r\n因为回源不能直接用服务器 IP （有多个站点），也不能用自己的域名（没备案），所以我用服务商自己的域名（他们的自己域名有他们自己的备案）。\r\n比如腾讯云服务器的网站用 site123.test.qcloud.com ，阿里云服务器的用 site123.test.aliyun.com 。\r\n```\r\n\r\n具体来说，就是自定义一个服务商子域名绑定服务器配置，在 Vercel 反代代码访问 http://自己的服务器 IP，指定 host 为服务商子域名，将返回 HTML 中的域名替换成自己在 Vercel 绑定的域名。后台管理是直连的，修改本地 hosts 把服务商子域名指向自己服务器 IP，当然也要使用 https，用的自签证书。\r\n\r\n感觉效果不错，分享给大家，这样大家买的国内服务器就可以用来建站了，不用吃灰了[doge]。\r\n\r\nVercel 在国内访问比其他同类产品要顺畅，不过听说反滥用很严格，只能跑点流量不大的网站，比如没什么人访问的个人博客[doge]。","content_rendered":"<p>如题。</p>\n<p>想搭些网站，买海外服务器太贵，买国内服务器又需要备案，研究了一下，最终决定买国内活动服务器，用 Vercel 作前端。</p>\n<p>Vercel 类似 Cloudflare Workers，支持 serverless code 和边缘缓存，相当于在上面跑了个反代，同时开启了缓存。</p>\n<pre><code>因为回源不能直接用服务器 IP （有多个站点），也不能用自己的域名（没备案），所以我用服务商自己的域名（他们的自己域名有他们自己的备案）。\n比如腾讯云服务器的网站用 site123.test.qcloud.com ，阿里云服务器的用 site123.test.aliyun.com 。\n</code></pre>\n<p>具体来说，就是自定义一个服务商子域名绑定服务器配置，在 Vercel 反代代码访问 http://自己的服务器 IP，指定 host 为服务商子域名，将返回 HTML 中的域名替换成自己在 Vercel 绑定的域名。后台管理是直连的，修改本地 hosts 把服务商子域名指向自己服务器 IP，当然也要使用 https，用的自签证书。</p>\n<p>感觉效果不错，分享给大家，这样大家买的国内服务器就可以用来建站了，不用吃灰了[doge]。</p>\n<p>Vercel 在国内访问比其他同类产品要顺畅，不过听说反滥用很严格，只能跑点流量不大的网站，比如没什么人访问的个人博客[doge]。</p>\n","last_modified":1616115042,"replies":8,"id":763047},{"node":{"avatar_large":"https://cdn.v2ex.com/navatar/c20a/d4d7/12_large.png?m=1615112532","name":"qna","avatar_normal":"https://cdn.v2ex.com/navatar/c20a/d4d7/12_normal.png?m=1615112532","title":"问与答","url":"https://www.v2ex.com/go/qna","topics":170337,"footer":"","header":"一个更好的世界需要你持续地提出好问题。","title_alternative":"Questions and Answers","avatar_mini":"https://cdn.v2ex.com/navatar/c20a/d4d7/12_mini.png?m=1615112532","stars":3188,"aliases":[],"root":false,"id":12,"parent_node_name":"v2ex"},"member":{"username":"zhoudaiyu","website":"","github":"","psn":"","avatar_normal":"https://cdn.v2ex.com/avatar/b75f/9ee0/163414_mini.png?m=1574570790","bio":"","url":"https://www.v2ex.com/u/zhoudaiyu","tagline":"","twitter":"","created":1458024699,"avatar_large":"https://cdn.v2ex.com/avatar/b75f/9ee0/163414_mini.png?m=1574570790","avatar_mini":"https://cdn.v2ex.com/avatar/b75f/9ee0/163414_mini.png?m=1574570790","location":"","btc":"","id":163414},"last_reply_by":"zhoudaiyu","last_touched":1616116975,"title":"为什么 supervisor 要求它启动的所有进程必须是前台启动的？","url":"https://www.v2ex.com/t/763050","created":1616115300,"content":"如果是后台启动的，那它也会拉起进程，但是 supervisor 认为进程退出了，进程就脱离它的控制了。如果进程只能后台启动那应该怎么做？","content_rendered":"<p>如果是后台启动的，那它也会拉起进程，但是 supervisor 认为进程退出了，进程就脱离它的控制了。如果进程只能后台启动那应该怎么做？</p>\n","last_modified":1616115300,"replies":7,"id":763050},{"node":{"avatar_large":"https://cdn.v2ex.com/navatar/c20a/d4d7/12_large.png?m=1615112532","name":"qna","avatar_normal":"https://cdn.v2ex.com/navatar/c20a/d4d7/12_normal.png?m=1615112532","title":"问与答","url":"https://www.v2ex.com/go/qna","topics":170337,"footer":"","header":"一个更好的世界需要你持续地提出好问题。","title_alternative":"Questions and Answers","avatar_mini":"https://cdn.v2ex.com/navatar/c20a/d4d7/12_mini.png?m=1615112532","stars":3188,"aliases":[],"root":false,"id":12,"parent_node_name":"v2ex"},"member":{"username":"TomVista","website":null,"github":null,"psn":null,"avatar_normal":"https://cdn.v2ex.com/gravatar/70fca85ee1d01e1d3b46ad99e7833bdf?s=24&d=retro","bio":null,"url":"https://www.v2ex.com/u/TomVista","tagline":null,"twitter":null,"created":1541550757,"avatar_large":"https://cdn.v2ex.com/gravatar/70fca85ee1d01e1d3b46ad99e7833bdf?s=24&d=retro","avatar_mini":"https://cdn.v2ex.com/gravatar/70fca85ee1d01e1d3b46ad99e7833bdf?s=24&d=retro","location":null,"btc":null,"id":361348},"last_reply_by":"iMiata","last_touched":1616117468,"title":"新人入职之后工作的问题,求解","url":"https://www.v2ex.com/t/763042","created":1616114216,"content":"前情提要:\r\n\r\n前端 3 年,入职 4 天,\r\n\r\n1. 大概多长时间梳理完代码,正式进入业务开发,(我已经完成 2.5 个业务中台展示和增删查改)\r\n\r\n2. 没到过大公司,加班应该谁提出来,(是的,有个后端暗示我就加班)\r\n\r\n3. 直属领导外出,入职的时候就不在,我的工作目前是小组中后端分配的,目前的任务对我来说没有绝对的约束,是吗?\r\n\r\n\r\n### 然后就是吐槽了\r\n\r\n首先,很重要的是,有个奴才,暗示加班,\r\n\r\n然后也很重要的是,没有工作交接,给了个 git 地址,分配一下开发任务,入职 0 天,开始业务开发.(代码上给了一两个重点)\r\n\r\n\r\n很缺前端,是的,钉钉里还让员工推荐,我肯定是招过来救火的.去他妈的\r\n\r\n### 是的,已经有离职想法了,再观望一周,不行就及早撤,","content_rendered":"<p>前情提要:</p>\n<p>前端 3 年,入职 4 天,</p>\n<ol>\n<li>\n<p>大概多长时间梳理完代码,正式进入业务开发,(我已经完成 2.5 个业务中台展示和增删查改)</p>\n</li>\n<li>\n<p>没到过大公司,加班应该谁提出来,(是的,有个后端暗示我就加班)</p>\n</li>\n<li>\n<p>直属领导外出,入职的时候就不在,我的工作目前是小组中后端分配的,目前的任务对我来说没有绝对的约束,是吗?</p>\n</li>\n</ol>\n<h3>然后就是吐槽了</h3>\n<p>首先,很重要的是,有个奴才,暗示加班,</p>\n<p>然后也很重要的是,没有工作交接,给了个 git 地址,分配一下开发任务,入职 0 天,开始业务开发.(代码上给了一两个重点)</p>\n<p>很缺前端,是的,钉钉里还让员工推荐,我肯定是招过来救火的.去他妈的</p>\n<h3>是的,已经有离职想法了,再观望一周,不行就及早撤,</h3>\n","last_modified":1616114216,"replies":7,"id":763042}]