[{"node":{"avatar_large":"https://cdn.v2ex.com/navatar/4ea0/6fbc/770_large.png?m=1695370146","name":"career","avatar_normal":"https://cdn.v2ex.com/navatar/4ea0/6fbc/770_normal.png?m=1695370146","title":"职场话题","url":"https://www.v2ex.com/go/career","topics":14952,"footer":"","header":"这里，我们聊聊那些工作中遇到的开心和不开心的事。","title_alternative":"Career","avatar_mini":"https://cdn.v2ex.com/navatar/4ea0/6fbc/770_mini.png?m=1695370146","stars":2818,"aliases":[],"root":false,"id":770,"parent_node_name":"work"},"member":{"id":429891,"username":"idragonet","url":"https://www.v2ex.com/u/idragonet","website":"","twitter":null,"psn":null,"github":null,"btc":null,"location":"","tagline":"","bio":"","avatar_mini":"https://cdn.v2ex.com/avatar/3acd/5809/429891_mini.png?m=1694065185","avatar_normal":"https://cdn.v2ex.com/avatar/3acd/5809/429891_normal.png?m=1694065185","avatar_large":"https://cdn.v2ex.com/avatar/3acd/5809/429891_large.png?m=1694065185","created":1563323820,"last_modified":1694065185},"last_reply_by":"idragonet","last_touched":1697073181,"title":"公司饮水有异味，个人解决方案是否可行？","url":"https://www.v2ex.com/t/981173","created":1697071199,"deleted":0,"content":"现在公司过滤就是简简单单过滤然后烧开，出的开水异味很大！打算买米家小米米家台式净饮机乐享版（免安装，水箱设计适合办公室）。\r\n\r\nhttps://item.jd.com/100032762821.html","content_rendered":"<p>现在公司过滤就是简简单单过滤然后烧开，出的开水异味很大！打算买米家小米米家台式净饮机乐享版（免安装，水箱设计适合办公室）。</p>\n<p><a href=\"https://item.jd.com/100032762821.html\" rel=\"nofollow\">https://item.jd.com/100032762821.html</a></p>\n","last_modified":1697071270,"replies":13,"id":981173},{"node":{"avatar_large":"https://cdn.v2ex.com/navatar/e7b2/4b11/360_large.png?m=1670319927","name":"windows","avatar_normal":"https://cdn.v2ex.com/navatar/e7b2/4b11/360_normal.png?m=1670319927","title":"Windows","url":"https://www.v2ex.com/go/windows","topics":3408,"footer":"","header":"Windows, not walls.","title_alternative":"Windows","avatar_mini":"https://cdn.v2ex.com/navatar/e7b2/4b11/360_mini.png?m=1670319927","stars":1136,"aliases":[],"root":false,"id":360,"parent_node_name":"os"},"member":{"id":546403,"username":"Eathein","url":"https://www.v2ex.com/u/Eathein","website":null,"twitter":null,"psn":null,"github":null,"btc":null,"location":null,"tagline":null,"bio":null,"avatar_mini":"https://cdn.v2ex.com/gravatar/45e855ca9b6cc38c42fedc09dab1ca89?s=24&d=retro","avatar_normal":"https://cdn.v2ex.com/gravatar/45e855ca9b6cc38c42fedc09dab1ca89?s=48&d=retro","avatar_large":"https://cdn.v2ex.com/gravatar/45e855ca9b6cc38c42fedc09dab1ca89?s=73&d=retro","created":1622021369,"last_modified":1692362203},"last_reply_by":"lisxour","last_touched":1697073021,"title":"windows 重装后原来的软件必须重装才能用吗","url":"https://www.v2ex.com/t/981178","created":1697072093,"deleted":0,"content":"首先容我吐槽两句：\r\n\r\ncnm 的 steam ，我设置个手柄操作你就让我重启，我以为是重启 steam ，结果是让我重启电脑，你干嘛不说清楚，我后台游戏还跑着呢？\r\n\r\ncnm 的 windows ，为了能让任务栏图标居左且不自动合并，我参与了预览版计划，选的还是 beta 版本，虽然我知道预览版会有 bug ，但一个重启就把你干歇逼了，你怎么这么菜？\r\n\r\ncnm 的金士顿，把你做成个 pe 盘就是让你重装的时候用，结果你写保护了？没法用了，直接扔垃圾桶了。（可能不是 U 盘本身的锅，我也不知道咋就写保护了）（反手买了一个新的金士顿 U 盘）\r\n\r\n吐槽完毕。\r\n\r\n\r\n诚心请教，windows 在 C 盘重装系统，原来的装在 D 盘的大多数软件因为注册表的问题都没法用了，只能删了重新装。所以有什么办法能让每次重装系统后将软件快速恢复吗？\r\n\r\n我想到的方向：\r\n\r\n1 、windows 是否有软件能够一键安装自己常用的软件？\r\n\r\n2 、既然是注册表出的问题，那我重装前导出注册表，重装后把原来的注册表导入新系统是否有效？会对新系统有不好的影响吗？\r\n\r\n3 、windows 的系统还原点好用吗？比如建一个 C 盘的系统还原点，电脑出问题后回滚到这个还原点是否系统就正常了？","content_rendered":"<p>首先容我吐槽两句：</p>\n<p>cnm 的 steam ，我设置个手柄操作你就让我重启，我以为是重启 steam ，结果是让我重启电脑，你干嘛不说清楚，我后台游戏还跑着呢？</p>\n<p>cnm 的 windows ，为了能让任务栏图标居左且不自动合并，我参与了预览版计划，选的还是 beta 版本，虽然我知道预览版会有 bug ，但一个重启就把你干歇逼了，你怎么这么菜？</p>\n<p>cnm 的金士顿，把你做成个 pe 盘就是让你重装的时候用，结果你写保护了？没法用了，直接扔垃圾桶了。（可能不是 U 盘本身的锅，我也不知道咋就写保护了）（反手买了一个新的金士顿 U 盘）</p>\n<p>吐槽完毕。</p>\n<p>诚心请教，windows 在 C 盘重装系统，原来的装在 D 盘的大多数软件因为注册表的问题都没法用了，只能删了重新装。所以有什么办法能让每次重装系统后将软件快速恢复吗？</p>\n<p>我想到的方向：</p>\n<p>1 、windows 是否有软件能够一键安装自己常用的软件？</p>\n<p>2 、既然是注册表出的问题，那我重装前导出注册表，重装后把原来的注册表导入新系统是否有效？会对新系统有不好的影响吗？</p>\n<p>3 、windows 的系统还原点好用吗？比如建一个 C 盘的系统还原点，电脑出问题后回滚到这个还原点是否系统就正常了？</p>\n","last_modified":1697072093,"replies":9,"id":981178}]